ncdjango/__init__.py
ncdjango/api.py
ncdjango/config.py
ncdjango/exceptions.py
ncdjango/fields.py
ncdjango/forms.py
ncdjango/geoimage.py
ncdjango/geoprocessing/__init__.py
ncdjango/geoprocessing/celery_tasks.py
ncdjango/geoprocessing/data.py
ncdjango/geoprocessing/evaluation.py
ncdjango/geoprocessing/exceptions.py
ncdjango/geoprocessing/params.py
ncdjango/geoprocessing/serializers.py
ncdjango/geoprocessing/tasks/__init__.py
ncdjango/geoprocessing/tasks/raster.py
ncdjango/geoprocessing/test_data/map_reduce_workflow.json
ncdjango/geoprocessing/test_data/simple_grid_2d.nc
ncdjango/geoprocessing/urls.py
ncdjango/geoprocessing/utils.py
ncdjango/geoprocessing/views.py
ncdjango/geoprocessing/workflow.py
ncdjango/interfaces/__init__.py
ncdjango/interfaces/arcgis/__init__.py
ncdjango/interfaces/arcgis/form_fields.py
ncdjango/interfaces/arcgis/forms.py
ncdjango/interfaces/arcgis/urls.py
ncdjango/interfaces/arcgis/utils.py
ncdjango/interfaces/arcgis/views.py
ncdjango/interfaces/arcgis/wkid.py
ncdjango/interfaces/arcgis_extended/__init__.py
ncdjango/interfaces/arcgis_extended/form_fields.py
ncdjango/interfaces/arcgis_extended/forms.py
ncdjango/interfaces/arcgis_extended/urls.py
ncdjango/interfaces/arcgis_extended/utils.py
ncdjango/interfaces/arcgis_extended/views.py
ncdjango/interfaces/data/__init__.py
ncdjango/interfaces/data/classify.py
ncdjango/interfaces/data/forms.py
ncdjango/interfaces/data/urls.py
ncdjango/interfaces/data/views.py
ncdjango/management/__init__.py
ncdjango/management/commands/__init__.py
ncdjango/management/commands/cleanup_temporary_services.py
ncdjango/middleware.py
ncdjango/migrations/0001_initial.py
ncdjango/migrations/0002_auto_20141001_1050.py
ncdjango/migrations/0003_auto_20151230_0954.py
ncdjango/migrations/__init__.py
ncdjango/models.py
ncdjango/tasks.py
ncdjango/urls.py
ncdjango/utils.py
ncdjango/views.py
ncdjango-1.4.1.dist-info/METADATA
ncdjango-1.4.1.dist-info/WHEEL
ncdjango-1.4.1.dist-info/licenses/LICENSE
ncdjango-1.4.1.dist-info/RECORD
