Metadata-Version: 2.4
Name: ncdjango
Version: 1.4.1
Summary: A NetCDF mapserver app for Django
License: BSD-3-Clause
License-File: LICENSE
Author: Conservation Biology Institute
Requires-Python: >=3.10,<3.12
Classifier: Development Status :: 5 - Production/Stable
Classifier: License :: OSI Approved :: BSD License
Classifier: Programming Language :: Python :: 3
Classifier: Programming Language :: Python :: 3.10
Classifier: Programming Language :: Python :: 3.11
Requires-Dist: Django (>=5.2.0)
Requires-Dist: Fiona
Requires-Dist: Pillow (>=9.0.1,<11.0.0)
Requires-Dist: Shapely (>=1.7.0)
Requires-Dist: celery (>=5.2.3,<6.0.0)
Requires-Dist: django-tastypie (>=0.14.0,<0.15.0)
Requires-Dist: djangorestframework
Requires-Dist: netCDF4 (>=1.5.3)
Requires-Dist: numpy (>=1.24,<2.0)
Requires-Dist: ply
Requires-Dist: pyproj
Requires-Dist: rasterio
Requires-Dist: requests
Requires-Dist: trefoil (>=0.4.2,<0.5.0)
